PyLinuxPorts/PyLinuxPorts.py
py_linux_ports-0.0.3.dist-info/LICENSE
py_linux_ports-0.0.3.dist-info/METADATA
py_linux_ports-0.0.3.dist-info/WHEEL
py_linux_ports-0.0.3.dist-info/top_level.txt
py_linux_ports-0.0.3.dist-info/RECORD
