Metadata-Version: 2.1
Name: py-linux-ports
Version: 0.0.3
Summary: Check Linux System Port's Status.
Home-page: https://github.com/sujitmandal/py-linux-ports
Author: Sujit Mandal
Author-email: mandals974@gmail.com
License: MIT
Platform: UNKNOWN
Classifier: License :: OSI Approved :: MIT License
Classifier: Programming Language :: Python :: 2.7
Classifier: Programming Language :: Python :: 3.0
Classifier: Programming Language :: Python :: 3.5
Classifier: Programming Language :: Python :: 3.6
Classifier: Programming Language :: Python :: 3.7
Classifier: Programming Language :: Python :: 3.8
Classifier: Programming Language :: Python :: 3.9
